pynetbox/__init__.py
pynetbox/core/__init__.py
pynetbox/core/api.py
pynetbox/core/app.py
pynetbox/core/endpoint.py
pynetbox/core/query.py
pynetbox/core/response.py
pynetbox/core/util.py
pynetbox/models/__init__.py
pynetbox/models/circuits.py
pynetbox/models/dcim.py
pynetbox/models/extras.py
pynetbox/models/ipam.py
pynetbox/models/mapper.py
pynetbox/models/users.py
pynetbox/models/virtualization.py
pynetbox/models/wireless.py
pynetbox-7.4.1.dist-info/LICENSE
pynetbox-7.4.1.dist-info/METADATA
pynetbox-7.4.1.dist-info/WHEEL
pynetbox-7.4.1.dist-info/top_level.txt
pynetbox-7.4.1.dist-info/RECORD
