Metadata-Version: 2.1
Name: pynetbox
Version: 7.4.1
Summary: NetBox API client library
Home-page: https://github.com/netbox-community/pynetbox
Author: Zach Moody, Arthur Hanson
Author-email: ahanson@netboxlabs.com
License: Apache2
Keywords: netbox
Classifier: Intended Audience :: Developers
Classifier: Development Status :: 5 - Production/Stable
Classifier: Programming Language :: Python :: 3
Classifier: Programming Language :: Python :: 3.10
Classifier: Programming Language :: Python :: 3.11
Classifier: Programming Language :: Python :: 3.12
License-File: LICENSE
Requires-Dist: requests<3.0,>=2.20.0
Requires-Dist: packaging
